setup.cfg
setup.py
examples/__init__.py
examples/colors.py
examples/calculations/__init__.py
examples/calculations/bayes_rule.py
examples/distributions/__init__.py
examples/distributions/conjugate/__init__.py
examples/distributions/conjugate/_gamma_normal_conjugate.py
examples/distributions/conjugate/_inv_gamma_normal_conjugate.py
examples/distributions/conjugate/beta_binomial_conjugate.py
examples/distributions/conjugate/beta_geometric_conjugate.py
examples/distributions/conjugate/dirichlet_multinomial_conjugate.py
examples/distributions/conjugate/gamma_exponential_conjugate.py
examples/distributions/conjugate/gamma_poisson_conjugate.py
examples/distributions/conjugate/normal_normal_conjugate.py
examples/distributions/continuous/__init__.py
examples/distributions/continuous/beta.py
examples/distributions/continuous/comparisons.py
examples/distributions/continuous/dirichlet.py
examples/distributions/continuous/exponential.py
examples/distributions/continuous/gamma.py
examples/distributions/continuous/inverse_gamma.py
examples/distributions/continuous/laplace.py
examples/distributions/continuous/lomax.py
examples/distributions/continuous/normal.py
examples/distributions/continuous/pert.py
examples/distributions/continuous/students_t.py
examples/distributions/discrete/__init__.py
examples/distributions/discrete/beta_binomial.py
examples/distributions/discrete/binomial.py
examples/distributions/discrete/geometric.py
examples/distributions/discrete/hyper_geometric.py
examples/distributions/discrete/multinomial.py
examples/distributions/discrete/negative_binomial.py
examples/distributions/discrete/poisson.py
examples/distributions/multivariate/__init__.py
examples/distributions/multivariate/dirichlet.py
examples/distributions/multivariate/mv_normal.py
examples/models/__init__.py
examples/models/project_network.py
examples/models/decision_tree/__init__.py
examples/models/decision_tree/decision_tree__fixed.py
examples/models/decision_tree/decision_tree__from_actions.py
probability.egg-info/PKG-INFO
probability.egg-info/SOURCES.txt
probability.egg-info/dependency_links.txt
probability.egg-info/requires.txt
probability.egg-info/top_level.txt
