Metadata-Version: 1.1
Name: probability
Version: 0.0.162
Summary: Probability in Python 3
Home-page: https://github.com/vahndi/probability
Author: Vahndi Minah
Author-email: UNKNOWN
License: MIT
Keywords: python,probability
Platform: UNKNOWN
Classifier: Development Status :: 3 - Alpha
Classifier: Intended Audience :: Developers
Classifier: License :: OSI Approved :: MIT License
Classifier: Programming Language :: Python :: 3
